explore/__init__.py
explore/abstract.py
explore-1.0.0.dist-info/LICENCE
explore-1.0.0.dist-info/METADATA
explore-1.0.0.dist-info/WHEEL
explore-1.0.0.dist-info/top_level.txt
explore-1.0.0.dist-info/RECORD
