Metadata-Version: 2.1
Name: explore
Version: 1.0.0
Summary: Scoring and best match picking.
Home-page: https://github.com/Exahilosys/explore
Author: UNKNOWN
Author-email: UNKNOWN
License: MIT
Platform: UNKNOWN
